aws_audit/__init__.py
aws_audit/audit.py
aws_audit/configure.py
aws_audit/output.py
aws_audit/config/__init__.py
aws_audit/config/regions.py
aws_audit/config/rules.py
aws_audit/helper/__init__.py
aws_audit/helper/common.py
aws_audit/plugins/__init__.py
aws_audit/plugins/initialize.py
aws_audit/plugins/acm/__init__.py
aws_audit/plugins/acm/acmhandler.py
aws_audit/plugins/apigateway/__init__.py
aws_audit/plugins/apigateway/apigatewayhandler.py
aws_audit/plugins/backup/__init__.py
aws_audit/plugins/backup/backuphandler.py
aws_audit/plugins/cloudfront/__init__.py
aws_audit/plugins/cloudfront/cloudfronthandler.py
aws_audit/plugins/cloudtrail/__init__.py
aws_audit/plugins/cloudtrail/cloudtrailhandler.py
aws_audit/plugins/config/__init__.py
aws_audit/plugins/config/confighandler.py
aws_audit/plugins/dms/__init__.py
aws_audit/plugins/dms/dmshandler.py
aws_audit/plugins/dynamodb/__init__.py
aws_audit/plugins/dynamodb/dynamodbhandler.py
aws_audit/plugins/ec2/__init__.py
aws_audit/plugins/ec2/ec2handler.py
aws_audit/plugins/ecr/__init__.py
aws_audit/plugins/ecr/ecrhandler.py
aws_audit/plugins/efs/__init__.py
aws_audit/plugins/efs/efshandler.py
aws_audit/plugins/eks/__init__.py
aws_audit/plugins/eks/ekshandler.py
aws_audit/plugins/elasticache/__init__.py
aws_audit/plugins/elasticache/elasticachehandler.py
aws_audit/plugins/elbv2/__init__.py
aws_audit/plugins/elbv2/elbv2handler.py
aws_audit/plugins/emr/__init__.py
aws_audit/plugins/emr/emrhandler.py
aws_audit/plugins/es/__init__.py
aws_audit/plugins/es/eshandler.py
aws_audit/plugins/firehose/__init__.py
aws_audit/plugins/firehose/firehosehandler.py
aws_audit/plugins/fsx/__init__.py
aws_audit/plugins/fsx/fsxhandler.py
aws_audit/plugins/iam/__init__.py
aws_audit/plugins/iam/iamhandler.py
aws_audit/plugins/kafka/__init__.py
aws_audit/plugins/kafka/kafkahandler.py
aws_audit/plugins/kinesis/__init__.py
aws_audit/plugins/kinesis/kinesishandler.py
aws_audit/plugins/kms/__init__.py
aws_audit/plugins/kms/kmshandler.py
aws_audit-0.1.0.dist-info/LICENSE
aws_audit-0.1.0.dist-info/METADATA
aws_audit-0.1.0.dist-info/WHEEL
aws_audit-0.1.0.dist-info/entry_points.txt
aws_audit-0.1.0.dist-info/top_level.txt
aws_audit-0.1.0.dist-info/RECORD
