Metadata-Version: 2.1
Name: aws-audit
Version: 0.1.0
Summary: This Utility will help you with the security audit of AWS cloud services.
Home-page: UNKNOWN
Author: TheCloudRecipes
Author-email: thecloudrecipes@gmail.com
License: UNKNOWN
Keywords: AWS,Amazon Web Services,Security,Audit,Infrastructure Audit,Security Audit,Python,Amazon,boto3,Cloud
Platform: UNKNOWN
Classifier: Development Status :: 5 - Production/Stable
Classifier: Intended Audience :: Developers
Classifier: Intended Audience :: System Administrators
Classifier: Intended Audience :: Information Technology
Classifier: Programming Language :: Python :: 3.5
Classifier: Programming Language :: Python :: 3.6
Classifier: Programming Language :: Python :: 3.7
Classifier: Programming Language :: Python :: 3.8
Classifier: License :: OSI Approved :: GNU Affero General Public License v3 or later (AGPLv3+)
Classifier: Operating System :: OS Independent
Classifier: Topic :: System :: Systems Administration
Classifier: Topic :: Utilities
Requires-Python: >=3.5
Requires-Dist: boto3 (>=1.13.0)
Requires-Dist: python-dotenv (>=0.11.0)
Requires-Dist: pytz (>=2019.3)
Requires-Dist: xlsxwriter (>1.2.6)
Requires-Dist: tqdm (>=4.40.1)
